cidr/__init__.py
cidr/apps.py
cidr/middleware.py
tests/__init__.py
tests/settings.py
tests/test_middleware.py
django_cidr_allowed_hosts-1.0.3.dist-info/LICENSE
django_cidr_allowed_hosts-1.0.3.dist-info/METADATA
django_cidr_allowed_hosts-1.0.3.dist-info/WHEEL
django_cidr_allowed_hosts-1.0.3.dist-info/top_level.txt
django_cidr_allowed_hosts-1.0.3.dist-info/RECORD
