Metadata-Version: 2.1
Name: django-cidr-allowed-hosts
Version: 1.0.3
Summary: Django middleware to allow access from specific CIDR ranges
Home-page: https://github.com/wozniakpl/django-cidr-allowed-hosts.git
Author: Barton Woźniak
Author-email: bwozniakdev@protonmail.com
Classifier: Framework :: Django
Classifier: Framework :: Django :: 2.2
Classifier: Framework :: Django :: 3.2
Classifier: Framework :: Django :: 4.0
Classifier: Intended Audience :: Developers
Classifier: License :: OSI Approved :: MIT License
Classifier: Operating System :: OS Independent
Classifier: Natural Language :: English
Classifier: Programming Language :: Python
Classifier: Programming Language :: Python :: 3
Classifier: Programming Language :: Python :: 3.6
Classifier: Programming Language :: Python :: 3.7
Classifier: Programming Language :: Python :: 3.8
Classifier: Programming Language :: Python :: 3.9
License-File: LICENSE
Requires-Dist: Django (>=2.2)
